{
  "OfficeOfTheSamahanVicePresident": [
    {
      "fullName": "Sung Goon L. Acosta",
      "position": "SAMAHAN Vice President",
      "fileName": "VICE_PRESIDENT_Sung_Goon_L._Acosta.png"
    },
    {
      "fullName": "Hyacinth Louise R. Duldulao",
      "position": "Chief-of-Staff",
      "fileName": "Chief-of-Staff_Hyacinth_Louise_R._Duldulao.png"
    },
    {
      "fullName": "Winarni M. Bungabong",
      "position": "Deputy Chief-of-Staff",
      "fileName": "Deputy_Chief-of-Staff_Winarni_M._Bungabong.png"
    }
  ],
  "OfficeOfTheLegislativeSecretary": [
    {
      "fullName": "Joie Noreen G. Garces",
      "position": "Legislative Secretary",
      "fileName": "Legislative_Secretary_Joie_Noreen_G._Garces.png"
    },
    {
      "fullName": "Mikyla M. Josol",
      "position": "Legislative Undersecretary",
      "fileName": "Legislative_Undersecretary_Mikyla_M._Josol.png"
    }
  ],
  "DepartmentOfAcademicAffairs": [
    {
      "fullName": "Alessandra Marie Leyma",
      "position": "DAA Director",
      "fileName": "DAA_Director_Alessandra_Marie_Leyma.png"
    },
    {
      "fullName": "Shaira R. Alimpulos",
      "position": "DAA Deputy Director",
      "fileName": "DAA_Deputy_Director_Shaira_R._Alimpulos.png"
    }
  ],
  "DepartmentOfDisasterRiskReductionAndManagement": [
    {
      "fullName": "Alex Dave C. Escalante",
      "position": "DRRM Director",
      "fileName": "DRRM_Director_Alex_Dave_C._Escalante.png"
    },
    {
      "fullName": "Ethel Marren M. Guerra",
      "position": "DRRM Deputy Director",
      "fileName": "DRRM_Deputy_Director_Ethel_Marren_M._Guerra.png"
    }
  ],
  "SamahanPoliticalAffairsAndEngagementsDepartment": [
    {
      "fullName": "Iesha Jaesamin Twaye D. Bastian",
      "position": "SPAED Director",
      "fileName": "SPAED_Director_Iesha_Jaesamin_Twaye_D._Bastian.png"
    },
    {
      "fullName": "Luis Miguel L. Torres",
      "position": "SPAED Deputy Director",
      "fileName": "SPAED_Deputy_Director_Luis_Miguel_L._Torres.png"
    }
  ]
}